arowana/__init__.py
arowana/base.py
arowana/drive.py
arowana-0.1.3.dist-info/licenses/LICENSE
arowana-0.1.3.dist-info/METADATA
arowana-0.1.3.dist-info/WHEEL
arowana-0.1.3.dist-info/top_level.txt
arowana-0.1.3.dist-info/RECORD
