Metadata-Version: 2.4
Name: arowana
Version: 0.1.3
Summary: Data storage made simple
Author-email: SlumberDemon <hi@sofa.sh>
Project-URL: Fishweb, https://github.com/slumberdemon/fishweb
Project-URL: Bug Reports, https://github.com/slumberdemon/arowana/issues
Project-URL: Source, https://github.com/slumberdemon/arowana
Classifier: Programming Language :: Python
Requires-Python: >=3.9
License-File: LICENSE
Dynamic: license-file
